MANIFEST.in
README.rst
setup.cfg
setup.py
serpy/__init__.py
serpy/fields.py
serpy/serializer.py
serpy_ctp.egg-info/PKG-INFO
serpy_ctp.egg-info/SOURCES.txt
serpy_ctp.egg-info/dependency_links.txt
serpy_ctp.egg-info/requires.txt
serpy_ctp.egg-info/top_level.txt