Metadata-Version: 1.2
Name: serpy-ctp
Version: 0.2.1
Summary: ridiculously fast object serialization fork by canaltp
Home-page: https://github.com/canaltp/serpy
Maintainer: canaltp
Maintainer-email: navitia@canaltp.fr
License: MIT
Keywords: serialization,rest,json,api,marshal,marshalling,validation,schema,fast
Platform: UNKNOWN
Classifier: Development Status :: 4 - Beta
Classifier: Intended Audience :: Developers
Classifier: License :: OSI Approved :: MIT License
Classifier: Programming Language :: Python :: 2
Classifier: Programming Language :: Python :: 2.6
Classifier: Programming Language :: Python :: 2.7
Classifier: Programming Language :: Python :: 3
Classifier: Programming Language :: Python :: 3.3
Classifier: Programming Language :: Python :: 3.4
Classifier: Programming Language :: Python :: Implementation :: CPython
Classifier: Programming Language :: Python :: Implementation :: PyPy
Provides: serpy
